AUTHORS.md
LICENSE.txt
MANIFEST.in
README.md
modified.py
setup.py
modified.egg-info/PKG-INFO
modified.egg-info/SOURCES.txt
modified.egg-info/dependency_links.txt
modified.egg-info/top_level.txt